tornado_discovery/__init__.py
tornado_discovery/common.py
tornado_discovery/config.py
tornado_discovery/connection.py
tornado_discovery/listener.py
tornado_discovery/registrant.py
tornado_discovery-0.0.5.dist-info/LICENSE
tornado_discovery-0.0.5.dist-info/METADATA
tornado_discovery-0.0.5.dist-info/WHEEL
tornado_discovery-0.0.5.dist-info/top_level.txt
tornado_discovery-0.0.5.dist-info/RECORD
