Metadata-Version: 2.1
Name: tornado-discovery
Version: 0.0.5
Summary: service discovery based on tornado
Home-page: https://github.com/fiefdx/tornado_discovery
Author: fiefdx
Author-email: fiefdx@163.com
License: MIT
Platform: UNKNOWN
Classifier: License :: OSI Approved :: MIT License
Classifier: Programming Language :: Python :: 3
Classifier: Programming Language :: Python :: 3.7
Requires-Dist: tornado (>=5.1.1)
